mypackage/__init__.py
mypackage/main.py
Topsis_Yugal_401903007-0.0.7.dist-info/METADATA
Topsis_Yugal_401903007-0.0.7.dist-info/WHEEL
Topsis_Yugal_401903007-0.0.7.dist-info/top_level.txt
Topsis_Yugal_401903007-0.0.7.dist-info/RECORD
