Metadata-Version: 2.1
Name: Topsis-Yugal-401903007
Version: 0.0.7
Summary: Topsis Package
Author: Yugal Verma
Author-email: yugalverma047@gmail.com
License: UNKNOWN
Platform: UNKNOWN
Classifier: Programming Language :: Python :: 3
Classifier: License :: OSI Approved :: MIT License
Classifier: Operating System :: OS Independent
Requires-Python: >=3.6
